flowsym/__init__.py
flowsym/__version__.py
flowsym/cli.py
flowsym/flowsym.py
flowsym/data/FPbase_Spectra.csv
flowsym/data/FPbase_Spectra_updated.csv
flowsym/data/sample_output.fcs
flowsym/tests/__init__.py
flowsym/tests/test_flowsym.py
flowsym/tests/data/FPbase_Spectra.csv
flowsym/tests/data/FPbase_Spectra_updated.csv
flowsym/tests/data/sample_output.fcs
flowsym-0.2.4.dist-info/AUTHORS.rst
flowsym-0.2.4.dist-info/LICENSE
flowsym-0.2.4.dist-info/METADATA
flowsym-0.2.4.dist-info/WHEEL
flowsym-0.2.4.dist-info/entry_points.txt
flowsym-0.2.4.dist-info/top_level.txt
flowsym-0.2.4.dist-info/RECORD
