Metadata-Version: 2.1
Name: flowsym
Version: 0.2.4
Summary: A Python API for simulating flow cytometry data
Home-page: https://github.com/harmslab/flowsym
Author: Luis Perez Morales, Michael M. Shavlik
Author-email: lperezmo@uoregon.edu
License: MIT license
Keywords: flowsym
Platform: UNKNOWN
Classifier: Development Status :: 2 - Pre-Alpha
Classifier: Intended Audience :: Developers
Classifier: License :: OSI Approved :: MIT License
Classifier: Natural Language :: English
Classifier: Programming Language :: Python :: 3
Classifier: Programming Language :: Python :: 3.5
Classifier: Programming Language :: Python :: 3.6
Classifier: Programming Language :: Python :: 3.7
Classifier: Programming Language :: Python :: 3.8
Classifier: Programming Language :: Python :: Implementation :: CPython
Classifier: Programming Language :: Python :: Implementation :: PyPy
Requires-Python: >=3.6
